{"v":"5.4.1","fr":30,"ip":0,"op":150,"w":1000,"h":750,"nm":"Comp 2","ddd":0,"assets":[],"layers":[{"ddd":0,"ind":1,"ty":4,"nm":"I Outlines","sr":1,"ks":{"o":{"a":0,"k":100,"ix":11},"r":{"a":0,"k":0,"ix":10},"p":{"a":1,"k":[{"i":{"x":0.667,"y":1},"o":{"x":0.167,"y":0.167},"n":"0p667_1_0p167_0p167","t":82,"s":[1156,603,0],"e":[286,599,0],"to":[-145,-0.66666668653488,0],"ti":[53.6666679382324,30.8333339691162,0]},{"i":{"x":0.667,"y":1},"o":{"x":0.333,"y":0},"n":"0p667_1_0p333_0","t":96,"s":[286,599,0],"e":[834,418,0],"to":[-53.6666679382324,-30.8333339691162,0],"ti":[-91.3333358764648,30.1666660308838,0]},{"t":118}],"ix":2},"a":{"a":0,"k":[0,0,0],"ix":1},"s":{"a":1,"k":[{"i":{"x":[0.833,0.833,0.833],"y":[0.833,0.833,0.833]},"o":{"x":[0.167,0.167,0.167],"y":[0.167,0.167,0.167]},"n":["0p833_0p833_0p167_0p167","0p833_0p833_0p167_0p167","0p833_0p833_0p167_0p167"],"t":107,"s":[525.495,525.495,100],"e":[168,168,100]},{"t":118}],"ix":6}},"ao":0,"shapes":[{"ty":"gr","it":[{"ind":0,"ty":"sh","ix":1,"ks":{"a":0,"k":{"i":[[0,0],[0,0],[0,0],[0,0]],"o":[[0,0],[0,0],[0,0],[0,0]],"v":[[7.612,0],[25.714,0],[25.714,-83.986],[7.612,-83.986]],"c":true},"ix":2},"nm":"I","mn":"ADBE Vector Shape - Group","hd":false},{"ty":"st","c":{"a":0,"k":[0.090196078431,0.149019607843,0.960784313725,1],"ix":3},"o":{"a":0,"k":100,"ix":4},"w":{"a":0,"k":3,"ix":5},"lc":1,"lj":1,"ml":4,"ml2":{"a":0,"k":4,"ix":8},"nm":"Stroke 1","mn":"ADBE Vector Graphic - Stroke","hd":false},{"ty":"tr","p":{"a":0,"k":[0,0],"ix":2},"a":{"a":0,"k":[0,0],"ix":1},"s":{"a":0,"k":[100,100],"ix":3},"r":{"a":0,"k":0,"ix":6},"o":{"a":0,"k":100,"ix":7},"sk":{"a":0,"k":0,"ix":4},"sa":{"a":0,"k":0,"ix":5},"nm":"Transform"}],"nm":"I","np":2,"cix":2,"ix":1,"mn":"ADBE Vector Group","hd":false}],"ip":0,"op":150,"st":0,"bm":0},{"ddd":0,"ind":2,"ty":4,"nm":"P Outlines","sr":1,"ks":{"o":{"a":0,"k":100,"ix":11},"r":{"a":0,"k":0,"ix":10},"p":{"a":1,"k":[{"i":{"x":0.667,"y":1},"o":{"x":0.167,"y":0.167},"n":"0p667_1_0p167_0p167","t":68,"s":[1156,603,0],"e":[286,599,0],"to":[-145,-0.66666668653488,0],"ti":[593,0.66666668653488,0]},{"i":{"x":0.667,"y":1},"o":{"x":0.333,"y":0},"n":"0p667_1_0p333_0","t":82,"s":[286,599,0],"e":[-2402,599,0],"to":[-593,-0.66666668653488,0],"ti":[448,0,0]},{"i":{"x":0.667,"y":0.667},"o":{"x":0.167,"y":0.167},"n":"0p667_0p667_0p167_0p167","t":96,"s":[-2402,599,0],"e":[-2402,599,0],"to":[0,0,0],"ti":[0,0,0]},{"i":{"x":0.64,"y":0.837},"o":{"x":0.167,"y":0},"n":"0p64_0p837_0p167_0","t":107,"s":[-2402,599,0],"e":[700.944,421.908,0],"to":[504.95751953125,-28.9966087341309,0],"ti":[-617.912658691406,35.4829292297363,0]},{"t":118}],"ix":2},"a":{"a":0,"k":[0,0,0],"ix":1},"s":{"a":1,"k":[{"i":{"x":[0.833,0.833,0.833],"y":[0.833,0.833,0.833]},"o":{"x":[0.167,0.167,0.167],"y":[0.167,0.167,0.167]},"n":["0p833_0p833_0p167_0p167","0p833_0p833_0p167_0p167","0p833_0p833_0p167_0p167"],"t":107,"s":[525.495,525.495,100],"e":[168,168,100]},{"t":118}],"ix":6}},"ao":0,"shapes":[{"ty":"gr","it":[{"ind":0,"ty":"sh","ix":1,"ks":{"a":0,"k":{"i":[[0,0],[0,0],[0,0],[0,0],[-4.691,2.133],[-2.325,4.329],[0,4.819],[4.733,4.5],[7.718,0],[0,0]],"o":[[0,0],[0,0],[0,0],[3.326,-0.085],[4.69,-2.132],[2.324,-4.328],[0,-7.334],[-4.733,-4.499],[0,0],[0,0]],"v":[[8.891,0],[26.865,0],[26.865,-32.494],[37.355,-32.75],[49.381,-36.076],[59.903,-45.767],[63.389,-59.487],[56.289,-77.238],[37.611,-83.986],[8.891,-83.986]],"c":true},"ix":2},"nm":"P","mn":"ADBE Vector Shape - Group","hd":false},{"ind":1,"ty":"sh","ix":2,"ks":{"a":0,"k":{"i":[[0,0],[-2.431,-1.876],[0,-3.411],[2.153,-2.175],[3.027,0],[0,0],[0,0]],"o":[[4.478,0],[2.431,1.877],[0,2.985],[-2.154,2.175],[0,0],[0,0],[0,0]],"v":[[30.639,-69.146],[41.001,-66.332],[44.647,-58.4],[41.417,-50.66],[33.646,-47.398],[26.609,-47.398],[26.609,-68.89]],"c":true},"ix":2},"nm":"P","mn":"ADBE Vector Shape - Group","hd":false},{"ty":"mm","mm":1,"nm":"Merge Paths 1","mn":"ADBE Vector Filter - Merge","hd":false},{"ty":"st","c":{"a":0,"k":[0.090196078431,0.149019607843,0.960784313725,1],"ix":3},"o":{"a":0,"k":100,"ix":4},"w":{"a":0,"k":3,"ix":5},"lc":1,"lj":1,"ml":4,"ml2":{"a":0,"k":4,"ix":8},"nm":"Stroke 1","mn":"ADBE Vector Graphic - Stroke","hd":false},{"ty":"tr","p":{"a":0,"k":[0,0],"ix":2},"a":{"a":0,"k":[0,0],"ix":1},"s":{"a":0,"k":[100,100],"ix":3},"r":{"a":0,"k":0,"ix":6},"o":{"a":0,"k":100,"ix":7},"sk":{"a":0,"k":0,"ix":4},"sa":{"a":0,"k":0,"ix":5},"nm":"Transform"}],"nm":"P","np":4,"cix":2,"ix":1,"mn":"ADBE Vector Group","hd":false}],"ip":0,"op":150,"st":0,"bm":0},{"ddd":0,"ind":3,"ty":4,"nm":"A Outlines","sr":1,"ks":{"o":{"a":0,"k":100,"ix":11},"r":{"a":0,"k":0,"ix":10},"p":{"a":1,"k":[{"i":{"x":0.667,"y":1},"o":{"x":0.167,"y":0.167},"n":"0p667_1_0p167_0p167","t":53,"s":[1156,603,0],"e":[286,599,0],"to":[-145,-0.66666668653488,0],"ti":[593,0.66666668653488,0]},{"i":{"x":0.667,"y":1},"o":{"x":0.333,"y":0},"n":"0p667_1_0p333_0","t":67,"s":[286,599,0],"e":[-2402,599,0],"to":[-593,-0.66666668653488,0],"ti":[448,0,0]},{"i":{"x":0.667,"y":0.667},"o":{"x":0.167,"y":0.167},"n":"0p667_0p667_0p167_0p167","t":81,"s":[-2402,599,0],"e":[-2402,599,0],"to":[0,0,0],"ti":[0,0,0]},{"i":{"x":0.64,"y":0.829},"o":{"x":0.167,"y":0},"n":"0p64_0p829_0p167_0","t":107,"s":[-2402,599,0],"e":[544.944,421.908,0],"to":[504.95751953125,-28.9966087341309,0],"ti":[-617.912658691406,35.4829292297363,0]},{"t":118}],"ix":2},"a":{"a":0,"k":[0,0,0],"ix":1},"s":{"a":1,"k":[{"i":{"x":[0.833,0.833,0.833],"y":[0.833,0.833,0.833]},"o":{"x":[0.167,0.167,0.167],"y":[0.167,0.167,0.167]},"n":["0p833_0p833_0p167_0p167","0p833_0p833_0p167_0p167","0p833_0p833_0p167_0p167"],"t":107,"s":[525.495,525.495,100],"e":[168,168,100]},{"t":118}],"ix":6}},"ao":0,"shapes":[{"ty":"gr","it":[{"ind":0,"ty":"sh","ix":1,"ks":{"a":0,"k":{"i":[[0,0],[0,0],[0,0],[0,0],[0,0],[0,0],[0,0],[0,0]],"o":[[0,0],[0,0],[0,0],[0,0],[0,0],[0,0],[0,0],[0,0]],"v":[[4.03,0],[22.15,0],[28.734,-16.503],[60.965,-16.503],[67.688,0],[85.905,0],[51.69,-83.986],[37.666,-83.986]],"c":true},"ix":2},"nm":"A","mn":"ADBE Vector Shape - Group","hd":false},{"ind":1,"ty":"sh","ix":2,"ks":{"a":0,"k":{"i":[[0,0],[0,0],[0,0]],"o":[[0,0],[0,0],[0,0]],"v":[[54.764,-31.727],[34.806,-31.727],[44.679,-56.481]],"c":true},"ix":2},"nm":"A","mn":"ADBE Vector Shape - Group","hd":false},{"ty":"mm","mm":1,"nm":"Merge Paths 1","mn":"ADBE Vector Filter - Merge","hd":false},{"ty":"st","c":{"a":0,"k":[0.090196078431,0.149019607843,0.960784313725,1],"ix":3},"o":{"a":0,"k":100,"ix":4},"w":{"a":0,"k":3,"ix":5},"lc":1,"lj":1,"ml":4,"ml2":{"a":0,"k":4,"ix":8},"nm":"Stroke 1","mn":"ADBE Vector Graphic - Stroke","hd":false},{"ty":"tr","p":{"a":0,"k":[0,0],"ix":2},"a":{"a":0,"k":[0,0],"ix":1},"s":{"a":0,"k":[100,100],"ix":3},"r":{"a":0,"k":0,"ix":6},"o":{"a":0,"k":100,"ix":7},"sk":{"a":0,"k":0,"ix":4},"sa":{"a":0,"k":0,"ix":5},"nm":"Transform"}],"nm":"A","np":4,"cix":2,"ix":1,"mn":"ADBE Vector Group","hd":false}],"ip":0,"op":150,"st":0,"bm":0},{"ddd":0,"ind":4,"ty":4,"nm":"X Outlines","sr":1,"ks":{"o":{"a":0,"k":100,"ix":11},"r":{"a":0,"k":0,"ix":10},"p":{"a":1,"k":[{"i":{"x":0.667,"y":1},"o":{"x":0.167,"y":0.167},"n":"0p667_1_0p167_0p167","t":38,"s":[1156,603,0],"e":[286,599,0],"to":[-145,-0.66666668653488,0],"ti":[593,0.66666668653488,0]},{"i":{"x":0.667,"y":1},"o":{"x":0.333,"y":0},"n":"0p667_1_0p333_0","t":54,"s":[286,599,0],"e":[-2402,599,0],"to":[-593,-0.66666668653488,0],"ti":[500,0,0]},{"i":{"x":0.667,"y":1},"o":{"x":0.167,"y":0},"n":"0p667_1_0p167_0","t":67,"s":[-2402,599,0],"e":[-2714,599,0],"to":[-500,0,0],"ti":[0,0,0]},{"i":{"x":0.64,"y":0.838},"o":{"x":0.167,"y":0},"n":"0p64_0p838_0p167_0","t":107,"s":[-2714,599,0],"e":[406.944,421.908,0],"to":[504.95751953125,-28.9966087341309,0],"ti":[-617.912658691406,35.4829292297363,0]},{"t":118}],"ix":2},"a":{"a":0,"k":[0,0,0],"ix":1},"s":{"a":1,"k":[{"i":{"x":[0.833,0.833,0.833],"y":[0.833,0.833,0.833]},"o":{"x":[0.167,0.167,0.167],"y":[0.167,0.167,0.167]},"n":["0p833_0p833_0p167_0p167","0p833_0p833_0p167_0p167","0p833_0p833_0p167_0p167"],"t":107,"s":[525.495,525.495,100],"e":[168,168,100]},{"t":118}],"ix":6}},"ao":0,"shapes":[{"ty":"gr","it":[{"ind":0,"ty":"sh","ix":1,"ks":{"a":0,"k":{"i":[[0,0],[0,0],[0,0],[0,0],[0,0],[0,0],[0,0],[0,0],[0,0],[0,0],[0,0],[0,0]],"o":[[0,0],[0,0],[0,0],[0,0],[0,0],[0,0],[0,0],[0,0],[0,0],[0,0],[0,0],[0,0]],"v":[[31.872,-44.005],[2.367,0],[21.47,0],[41.346,-29.849],[61.321,0],[80.02,0],[50.814,-44.066],[77.397,-83.986],[58.679,-83.986],[41.224,-58.3],[24.354,-83.986],[5.117,-83.986]],"c":true},"ix":2},"nm":"X","mn":"ADBE Vector Shape - Group","hd":false},{"ty":"st","c":{"a":0,"k":[0.090196078431,0.149019607843,0.960784313725,1],"ix":3},"o":{"a":0,"k":100,"ix":4},"w":{"a":0,"k":3,"ix":5},"lc":1,"lj":1,"ml":4,"ml2":{"a":0,"k":4,"ix":8},"nm":"Stroke 1","mn":"ADBE Vector Graphic - Stroke","hd":false},{"ty":"tr","p":{"a":0,"k":[0,0],"ix":2},"a":{"a":0,"k":[0,0],"ix":1},"s":{"a":0,"k":[100,100],"ix":3},"r":{"a":0,"k":0,"ix":6},"o":{"a":0,"k":100,"ix":7},"sk":{"a":0,"k":0,"ix":4},"sa":{"a":0,"k":0,"ix":5},"nm":"Transform"}],"nm":"X","np":2,"cix":2,"ix":1,"mn":"ADBE Vector Group","hd":false}],"ip":0,"op":150,"st":0,"bm":0},{"ddd":0,"ind":5,"ty":4,"nm":"E Outlines","sr":1,"ks":{"o":{"a":0,"k":100,"ix":11},"r":{"a":0,"k":0,"ix":10},"p":{"a":1,"k":[{"i":{"x":0.65,"y":0.664},"o":{"x":0.167,"y":0.167},"n":"0p65_0p664_0p167_0p167","t":19,"s":[1156,603,0],"e":[336.758,599.026,0],"to":[-585.682800292969,-0.6584404706955,0],"ti":[628.509216308594,0.70658713579178,0]},{"i":{"x":0.667,"y":1},"o":{"x":0.341,"y":0.087},"n":"0p667_1_0p341_0p087","t":37,"s":[336.758,599.026,0],"e":[-2402,599,0],"to":[-7.85225677490234,-0.00882771983743,0],"ti":[456.459594726563,0.00426410650834,0]},{"i":{"x":0.667,"y":0.667},"o":{"x":0.167,"y":0.167},"n":"0p667_0p667_0p167_0p167","t":53,"s":[-2402,599,0],"e":[-2402,599,0],"to":[0,0,0],"ti":[0,0,0]},{"i":{"x":0.64,"y":0.812},"o":{"x":0.167,"y":0},"n":"0p64_0p812_0p167_0","t":107,"s":[-2402,599,0],"e":[282.944,421.908,0],"to":[504.95751953125,-28.9966087341309,0],"ti":[-617.912658691406,35.4829292297363,0]},{"t":118}],"ix":2},"a":{"a":0,"k":[0,0,0],"ix":1},"s":{"a":1,"k":[{"i":{"x":[0.833,0.833,0.833],"y":[0.833,0.833,0.833]},"o":{"x":[0.167,0.167,0.167],"y":[0.167,0.167,0.167]},"n":["0p833_0p833_0p167_0p167","0p833_0p833_0p167_0p167","0p833_0p833_0p167_0p167"],"t":107,"s":[525.495,525.495,100],"e":[168,168,100]},{"t":118}],"ix":6}},"ao":0,"shapes":[{"ty":"gr","it":[{"ind":0,"ty":"sh","ix":1,"ks":{"a":0,"k":{"i":[[0,0],[0,0],[0,0],[0,0],[0,0],[0,0],[0,0],[0,0],[0,0],[0,0],[0,0],[0,0]],"o":[[0,0],[0,0],[0,0],[0,0],[0,0],[0,0],[0,0],[0,0],[0,0],[0,0],[0,0],[0,0]],"v":[[8.635,0],[55.905,0],[55.905,-16.631],[26.737,-16.631],[26.737,-34.029],[55.905,-34.029],[55.905,-50.404],[26.737,-50.404],[26.737,-67.355],[55.905,-67.355],[55.905,-83.986],[8.635,-83.986]],"c":true},"ix":2},"nm":"E","mn":"ADBE Vector Shape - Group","hd":false},{"ty":"st","c":{"a":0,"k":[0.090196078431,0.149019607843,0.960784313725,1],"ix":3},"o":{"a":0,"k":100,"ix":4},"w":{"a":0,"k":3,"ix":5},"lc":1,"lj":1,"ml":4,"ml2":{"a":0,"k":4,"ix":8},"nm":"Stroke 1","mn":"ADBE Vector Graphic - Stroke","hd":false},{"ty":"tr","p":{"a":0,"k":[0,0],"ix":2},"a":{"a":0,"k":[0,0],"ix":1},"s":{"a":0,"k":[100,100],"ix":3},"r":{"a":0,"k":0,"ix":6},"o":{"a":0,"k":100,"ix":7},"sk":{"a":0,"k":0,"ix":4},"sa":{"a":0,"k":0,"ix":5},"nm":"Transform"}],"nm":"E","np":2,"cix":2,"ix":1,"mn":"ADBE Vector Group","hd":false}],"ip":0,"op":150,"st":0,"bm":0},{"ddd":0,"ind":6,"ty":4,"nm":"H Outlines","sr":1,"ks":{"o":{"a":0,"k":100,"ix":11},"r":{"a":0,"k":0,"ix":10},"p":{"a":1,"k":[{"i":{"x":0.667,"y":1},"o":{"x":0.167,"y":0.167},"n":"0p667_1_0p167_0p167","t":0,"s":[1156,603,0],"e":[286,599,0],"to":[-145,-0.66666668653488,0],"ti":[593,0.66666668653488,0]},{"i":{"x":0.667,"y":1},"o":{"x":0.333,"y":0},"n":"0p667_1_0p333_0","t":20,"s":[286,599,0],"e":[-2402,599,0],"to":[-593,-0.66666668653488,0],"ti":[448,0,0]},{"i":{"x":0.667,"y":0.667},"o":{"x":0.167,"y":0.167},"n":"0p667_0p667_0p167_0p167","t":38,"s":[-2402,599,0],"e":[-2402,599,0],"to":[0,0,0],"ti":[0,0,0]},{"i":{"x":0.64,"y":0.8},"o":{"x":0.167,"y":0},"n":"0p64_0p8_0p167_0","t":107,"s":[-2402,599,0],"e":[123.944,421.908,0],"to":[504.95751953125,-28.9966087341309,0],"ti":[-617.912658691406,35.4829292297363,0]},{"t":118}],"ix":2},"a":{"a":0,"k":[0,0,0],"ix":1},"s":{"a":1,"k":[{"i":{"x":[0.833,0.833,0.833],"y":[0.833,0.833,0.833]},"o":{"x":[0.167,0.167,0.167],"y":[0.167,0.167,0.167]},"n":["0p833_0p833_0p167_0p167","0p833_0p833_0p167_0p167","0p833_0p833_0p167_0p167"],"t":107,"s":[525.495,525.495,100],"e":[168,168,100]},{"t":118}],"ix":6}},"ao":0,"shapes":[{"ty":"gr","it":[{"ind":0,"ty":"sh","ix":1,"ks":{"a":0,"k":{"i":[[0,0],[0,0],[0,0],[0,0],[0,0],[0,0],[0,0],[0,0],[0,0],[0,0],[0,0],[0,0]],"o":[[0,0],[0,0],[0,0],[0,0],[0,0],[0,0],[0,0],[0,0],[0,0],[0,0],[0,0],[0,0]],"v":[[8.315,0],[26.417,0],[26.417,-33.39],[56.161,-33.39],[56.161,0],[74.263,0],[74.263,-83.986],[56.161,-83.986],[56.161,-51.62],[26.417,-51.62],[26.417,-83.986],[8.315,-83.986]],"c":true},"ix":2},"nm":"H","mn":"ADBE Vector Shape - Group","hd":false},{"ty":"st","c":{"a":0,"k":[0.090196078431,0.149019607843,0.960784313725,1],"ix":3},"o":{"a":0,"k":100,"ix":4},"w":{"a":0,"k":3,"ix":5},"lc":1,"lj":1,"ml":4,"ml2":{"a":0,"k":4,"ix":8},"nm":"Stroke 1","mn":"ADBE Vector Graphic - Stroke","hd":false},{"ty":"tr","p":{"a":0,"k":[0,0],"ix":2},"a":{"a":0,"k":[0,0],"ix":1},"s":{"a":0,"k":[100,100],"ix":3},"r":{"a":0,"k":0,"ix":6},"o":{"a":0,"k":100,"ix":7},"sk":{"a":0,"k":0,"ix":4},"sa":{"a":0,"k":0,"ix":5},"nm":"Transform"}],"nm":"H","np":2,"cix":2,"ix":1,"mn":"ADBE Vector Group","hd":false}],"ip":0,"op":150,"st":0,"bm":0}],"markers":[]}